pytik/__init__.py
pytik/__main__.py
pytik/extract.py
pytik/request.py
pytik/tiktok.py
pytok/__init__.py
pytok/__main__.py
pytok/extract.py
pytok/tiktok.py
pytik-0.2.1.dist-info/LICENSE
pytik-0.2.1.dist-info/METADATA
pytik-0.2.1.dist-info/WHEEL
pytik-0.2.1.dist-info/top_level.txt
pytik-0.2.1.dist-info/RECORD
