Metadata-Version: 2.1
Name: pytik
Version: 0.2.1
Summary: Python metadata scrapper for TikTok
Home-page: https://github.com/thengo1/pytik
Author: The Ngo
Author-email: thengocu@gmail.com
License: MIT
Project-URL: Read the Docs, https://pytik.readthedocs.io/en/latest
Platform: UNKNOWN
Classifier: Programming Language :: Python :: 3
Classifier: License :: OSI Approved :: MIT License
Classifier: Operating System :: OS Independent
Requires-Python: >=3.6
